README.md
setup.cfg
setup.py
mutual_implication_score/__init__.py
mutual_implication_score/mis_architecture.py
mutual_implication_score/mis_wrapper.py
mutual_implication_score.egg-info/PKG-INFO
mutual_implication_score.egg-info/SOURCES.txt
mutual_implication_score.egg-info/dependency_links.txt
mutual_implication_score.egg-info/requires.txt
mutual_implication_score.egg-info/top_level.txt