Metadata-Version: 2.1
Name: mutual-implication-score
Version: 0.0.0
Summary: Mutual implication score: a symmetric measure of text semantic similarity based on a RoBERTA model pretrained for natural language inference.
Home-page: https://github.com/skoltech-nlp/mutual_implication_score
Author: Nikolai Babakov and David Dale
Author-email: bbk_junior@mail.ru
License: MIT
Platform: UNKNOWN
Classifier: Development Status :: 3 - Alpha
Classifier: Programming Language :: Python :: 3
Classifier: Operating System :: OS Independent
